ucutils/__init__.py
ucutils/checkpoint.py
ucutils/cli.py
ucutils/emu.py
ucutils/arch/__init__.py
ucutils/arch/x32/__init__.py
ucutils/arch/x64/__init__.py
ucutils/plat/__init__.py
ucutils/plat/win.py
ucutils/plat/win32.py
ucutils/plat/win64.py
ucutils-0.3.3.dist-info/LICENSE.txt
ucutils-0.3.3.dist-info/METADATA
ucutils-0.3.3.dist-info/WHEEL
ucutils-0.3.3.dist-info/top_level.txt
ucutils-0.3.3.dist-info/RECORD
